{
    "features": [
        {
            "geometry": {
                "coordinates": [
                    -74.00993585586546,
                    40.73306780584109
                ],
                "type": "Point"
            },
            "properties": {
                "cartodb_id": 1,
                "created_at": "2014-03-28T07:24:52Z",
                "description": "The Ramrod",
                "name": "First stop on the LEeather Trail tour",
                "updated_at": "2014-03-28T07:25:38Z"
            },
            "type": "Feature"
        },
        {
            "geometry": {
                "coordinates": [
                    -74.00852233171463,
                    40.742060855405796
                ],
                "type": "Point"
            },
            "properties": {
                "cartodb_id": 2,
                "created_at": "2014-03-28T07:25:00Z",
                "description": "The Anvil",
                "name": null,
                "updated_at": "2014-03-28T07:25:45Z"
            },
            "type": "Feature"
        },
        {
            "geometry": {
                "coordinates": [
                    -74.00767207145691,
                    40.746883067966394
                ],
                "type": "Point"
            },
            "properties": {
                "cartodb_id": 3,
                "created_at": "2014-03-28T07:25:11Z",
                "description": "The Spike",
                "name": null,
                "updated_at": "2014-03-28T07:25:50Z"
            },
            "type": "Feature"
        },
        {
            "geometry": {
                "coordinates": [
                    -74.00739312171936,
                    40.74753331850713
                ],
                "type": "Point"
            },
            "properties": {
                "cartodb_id": 4,
                "created_at": "2014-03-28T07:25:21Z",
                "description": "The Eagle",
                "name": null,
                "updated_at": "2014-03-28T07:25:57Z"
            },
            "type": "Feature"
        }
    ],
    "type": "FeatureCollection"
}
